equitorium/__init__.py
equitorium/customize.py
equitorium/finstat.py
equitorium/technical.py
equitorium-0.0.2.dist-info/LICENSE.txt
equitorium-0.0.2.dist-info/METADATA
equitorium-0.0.2.dist-info/WHEEL
equitorium-0.0.2.dist-info/top_level.txt
equitorium-0.0.2.dist-info/RECORD
