Metadata-Version: 2.1
Name: equitorium
Version: 0.0.2
Summary: To identify the investment opportunity in Bursa Market (KLSE)
Home-page: https://github.com/WongYC19/Equitorium
Author: YC WONG
Author-email: ycfkjc@hotmail.com
License: UNKNOWN
Keywords: bursa,KLSE,Technical Analysis,finance,investment,screener
Platform: UNKNOWN
Classifier: Programming Language :: Python :: 3
Classifier: License :: OSI Approved :: MIT License
Classifier: Operating System :: OS Independent
Requires-Python: >=3.7
Requires-Dist: numpy
Requires-Dist: pandas
Requires-Dist: tqdm
Requires-Dist: scipy
Requires-Dist: pyarrow
Requires-Dist: plotly
Requires-Dist: scikit-learn
Requires-Dist: dashtable
Requires-Dist: dash
